firmware_variables/__init__.py
firmware_variables/bindings.py
firmware_variables/boot.py
firmware_variables/device_path.py
firmware_variables/load_option.py
firmware_variables/privileges.py
firmware_variables/utils.py
firmware_variables/variables.py
firmware_variables-0.0.3.dist-info/LICENSE.txt
firmware_variables-0.0.3.dist-info/METADATA
firmware_variables-0.0.3.dist-info/WHEEL
firmware_variables-0.0.3.dist-info/top_level.txt
firmware_variables-0.0.3.dist-info/RECORD
